discord/ext/reactioncommands/__init__.py
discord/ext/reactioncommands/reactionbot.py
discord/ext/reactioncommands/reactioncontext.py
discord/ext/reactioncommands/reactioncore.py
discord/ext/reactioncommands/reactionerrors.py
discord/ext/reactioncommands/reactionhelp.py
discord/ext/reactioncommands/reactionproxy.py
discord/ext/reactioncommands/utils.py
ext_reactions-0.2.0.dist-info/LICENSE
ext_reactions-0.2.0.dist-info/METADATA
ext_reactions-0.2.0.dist-info/WHEEL
ext_reactions-0.2.0.dist-info/top_level.txt
ext_reactions-0.2.0.dist-info/RECORD
