Metadata-Version: 2.1
Name: ext-reactions
Version: 0.2.0
Summary: discord.py extension that adds reaction commands
Home-page: https://github.com/z03h/ReactionCommandBot
Author: z03h
License: MIT
Platform: UNKNOWN
Requires-Python: >=3.6.4
Requires-Dist: discord.py (<1.7.0,>=1.6.0)
